lean4check/__init__.py
lean4check/main.py
lean4check-0.1.1.dist-info/licenses/LICENSE
lean4check-0.1.1.dist-info/METADATA
lean4check-0.1.1.dist-info/WHEEL
lean4check-0.1.1.dist-info/entry_points.txt
lean4check-0.1.1.dist-info/top_level.txt
lean4check-0.1.1.dist-info/RECORD
